postmodal/__init__.py
postmodal/comparison/__init__.py
postmodal/comparison/mac.py
postmodal/comparison/matrix.py
postmodal/complexity.py
postmodal/manipulation/__init__.py
postmodal/manipulation/conversion.py
postmodal/manipulation/normalize.py
postmodal/manipulation/phase.py
postmodal/types.py
postmodal/validation.py
postmodal/visualization.py
postmodal-0.2.1.dist-info/LICENSE
postmodal-0.2.1.dist-info/METADATA
postmodal-0.2.1.dist-info/WHEEL
postmodal-0.2.1.dist-info/RECORD
