Metadata-Version: 2.1
Name: postmodal
Version: 0.2.1
Summary: Postprocessing of modal parameters from structural dynamics.
Home-page: https://github.com/runlevel0/postmodal
Author: Patrick Simon
Author-email: mail@patricksimon.info
Requires-Python: >=3.10,<3.14
Classifier: Programming Language :: Python :: 3
Classifier: Programming Language :: Python :: 3.10
Classifier: Programming Language :: Python :: 3.11
Classifier: Programming Language :: Python :: 3.12
Requires-Dist: matplotlib (>=3.7.0)
Requires-Dist: numpy (>=1.24.0)
Project-URL: Documentation, https://runlevel0.github.io/postmodal/
Project-URL: Repository, https://github.com/runlevel0/postmodal
